discordhtml/__init__.py
discordhtml/bot.py
discordhtml/errors.py
discordhtml/parser.py
discordhtml/utils.py
discordhtml/commands/__init__.py
discordhtml/commands/core.py
discordhtml/commands/params.py
discordhtml/commands/actions/__init__.py
discordhtml/commands/actions/core.py
discordhtml/commands/actions/default.py
discord.html-0.0.8.dist-info/LICENSE
discord.html-0.0.8.dist-info/METADATA
discord.html-0.0.8.dist-info/WHEEL
discord.html-0.0.8.dist-info/dependency_links.txt
discord.html-0.0.8.dist-info/top_level.txt
discord.html-0.0.8.dist-info/RECORD
