Metadata-Version: 2.1
Name: discord.html
Version: 0.0.8
Summary: A package to interact with the Discord API by writing HTML
Author: DistortedPumpkin
Classifier: Programming Language :: Python :: 3
Classifier: License :: OSI Approved :: MIT License
Classifier: Operating System :: OS Independent
Classifier: Development Status :: 2 - Pre-Alpha
Requires-Python: >=3.8.0
License-File: LICENSE
Requires-Dist: discord.py
Requires-Dist: bs4
